example_app/__init__.py
example_app/example.py
example_app_kc-0.0.27.dist-info/METADATA
example_app_kc-0.0.27.dist-info/WHEEL
example_app_kc-0.0.27.dist-info/top_level.txt
example_app_kc-0.0.27.dist-info/RECORD
